{"username":"er","password":"er","id":"95862987064800","level":0,"exp":0,"money":1000,"selectedDeck":{"deck":["fierywaraxe","evasivewyrm","blessingoftheancients","tastyflyfish","lightforgedblessing","depthcharge","cobaltspellkin","koboldstickyfinger","tombwarden","dreadscale"],"hero":{"name":"Warlock","heroPowerManaCost":3,"pcarts":[],"canAttack":false,"dcarts":["fierywaraxe","evasivewyrm","blessingoftheancients","tastyflyfish","lightforgedblessing","depthcharge","cobaltspellkin","koboldstickyfinger","tombwarden","dreadscale"],"spcarts":["darkskies","dreadscale"],"heroPower":"Decrease 2 HP , do randomly : \n 1) Add 1 HP and 1 ATT to a random minion (if there is) \n 2) Add a card from your deck and add it to your hand .","hp":35,"att":0,"specialPower":"This hero has 35 HP at the start of the game ."},"mostUsedCard":null,"totalPlays":0,"totalWins":0,"name":"Default Deck"},"allDecks":{"Default Deck":{"deck":["fierywaraxe","evasivewyrm","blessingoftheancients","tastyflyfish","lightforgedblessing","depthcharge","cobaltspellkin","koboldstickyfinger","tombwarden","dreadscale"],"hero":{"name":"Warlock","heroPowerManaCost":3,"pcarts":[],"canAttack":false,"dcarts":["fierywaraxe","evasivewyrm","blessingoftheancients","tastyflyfish","lightforgedblessing","depthcharge","cobaltspellkin","koboldstickyfinger","tombwarden","dreadscale"],"spcarts":["darkskies","dreadscale"],"heroPower":"Decrease 2 HP , do randomly : \n 1) Add 1 HP and 1 ATT to a random minion (if there is) \n 2) Add a card from your deck and add it to your hand .","hp":35,"att":0,"specialPower":"This hero has 35 HP at the start of the game ."},"mostUsedCard":null,"totalPlays":0,"totalWins":0,"name":"Default Deck"}},"newToGame":false,"playerHeroes":["warlock"],"playerCarts":["fierywaraxe","evasivewyrm","blessingoftheancients","tastyflyfish","lightforgedblessing","depthcharge","cobaltspellkin","koboldstickyfinger","tombwarden","dreadscale"]}